gotham/__init__.py
gotham/_core/__init__.py
gotham/_core/api_client.py
gotham/_core/auth_utils.py
gotham/_core/binary_stream.py
gotham/_core/compute_module_pipeline_auth.py
gotham/_core/confidential_client_auth.py
gotham/_core/config.py
gotham/_core/http_client.py
gotham/_core/oauth_utils.py
gotham/_core/page_iterator.py
gotham/_core/public_client_auth.py
gotham/_core/resource_iterator.py
gotham/_core/user_token_auth_client.py
gotham/_core/utils.py
gotham/_errors/__init__.py
gotham/_errors/api_not_found.py
gotham/_errors/connection_error.py
gotham/_errors/environment_not_configured.py
gotham/_errors/not_authenticated.py
gotham/_errors/palantir_exception.py
gotham/_errors/palantir_rpc_exception.py
gotham/_errors/sdk_internal_error.py
gotham/_errors/stream_error.py
gotham/_errors/timeout_error.py
gotham/_errors/utils.py
gotham/_versions.py
gotham/py.typed
gotham/v1/__init__.py
gotham/v1/cli.py
gotham/v1/client.py
gotham/v1/federated_sources/__init__.py
gotham/v1/federated_sources/_client.py
gotham/v1/federated_sources/errors.py
gotham/v1/federated_sources/federated_source.py
gotham/v1/federated_sources/models.py
gotham/v1/foundry/errors.py
gotham/v1/foundry/models.py
gotham/v1/gaia/__init__.py
gotham/v1/gaia/_client.py
gotham/v1/gaia/errors.py
gotham/v1/gaia/map.py
gotham/v1/gaia/models.py
gotham/v1/geotime/__init__.py
gotham/v1/geotime/_client.py
gotham/v1/geotime/errors.py
gotham/v1/geotime/geotime.py
gotham/v1/geotime/models.py
gotham/v1/gotham/errors.py
gotham/v1/gotham/models.py
gotham/v1/inbox/__init__.py
gotham/v1/inbox/_client.py
gotham/v1/inbox/errors.py
gotham/v1/inbox/messages.py
gotham/v1/inbox/models.py
gotham/v1/map_rendering/__init__.py
gotham/v1/map_rendering/_client.py
gotham/v1/map_rendering/errors.py
gotham/v1/map_rendering/map_rendering.py
gotham/v1/map_rendering/models.py
gotham/v1/media/__init__.py
gotham/v1/media/_client.py
gotham/v1/media/errors.py
gotham/v1/media/media.py
gotham/v1/media/models.py
gotham/v1/target_workbench/__init__.py
gotham_platform_python-0.1.0.dist-info/LICENSE
gotham_platform_python-0.1.0.dist-info/METADATA
gotham_platform_python-0.1.0.dist-info/WHEEL
gotham_platform_python-0.1.0.dist-info/entry_points.txt
gotham_platform_python-0.1.0.dist-info/RECORD
